opencensus/__init__.py
opencensus/ext/__init__.py
opencensus/ext/django/__init__.py
opencensus/ext/django/middleware.py
opencensus_ext_django-0.8.0.dist-info/METADATA
opencensus_ext_django-0.8.0.dist-info/WHEEL
opencensus_ext_django-0.8.0.dist-info/namespace_packages.txt
opencensus_ext_django-0.8.0.dist-info/top_level.txt
opencensus_ext_django-0.8.0.dist-info/RECORD
